msteamsnotifiers.py
msteamsnotifiers-0.3.0.dist-info/LICENSE
msteamsnotifiers-0.3.0.dist-info/WHEEL
msteamsnotifiers-0.3.0.dist-info/METADATA
msteamsnotifiers-0.3.0.dist-info/RECORD
