Metadata-Version: 2.3
Name: msteamsnotifiers
Version: 0.3.0
Summary: msteamsnotifiers: Decorators for automatically notifying an MS Teams channel of events
Author-email: Josh Burnett <josh@burnettsonline.org>
Requires-Python: >=3.8
Classifier: License :: OSI Approved :: MIT License
Requires-Dist: friendly_traceback
Project-URL: Home, https://github.com/joshburnett/msteamsnotifiers
